pycold.libs/libquadmath-96973f99.so.0.0.0
pycold.libs/libgfortran-040039e1.so.5.0.0
pycold.libs/libgsl-e0ea2ebb.so.27.0.0
pycold.libs/libgslcblas-70a60566.so.0.0.0
pycold-0.1.2.dist-info/METADATA
pycold-0.1.2.dist-info/LICENSE
pycold-0.1.2.dist-info/top_level.txt
pycold-0.1.2.dist-info/WHEEL
pycold-0.1.2.dist-info/RECORD
pycold/app.py
pycold/_param_validation.py
pycold/utils.py
pycold/__init__.py
pycold/ob_parameters.yaml
pycold/monkey.py
pycold/ob_analyst.py
pycold/_colds_cython.cpython-311-x86_64-linux-gnu.so
pycold/colds.py
pycold/pyclassifier.py
pycold/constants.yaml
pycold/common.py
pycold/imagetool/config.yaml
pycold/imagetool/__init__.py
pycold/imagetool/tile_processing.py
pycold/imagetool/export_change_map.py
pycold/imagetool/singlepath_landsat_conus.tif
pycold/imagetool/prepare_ard.py
