Metadata-Version: 2.1
Name: pycold
Version: 0.1.2
Summary: python implementation of COntinuous monitoring of Land disturbances algorithm
Home-page: https://github.com/GERSL/pycold
Author: Su Ye
Author-email: remotesensingsuy@gmail.com
License: Apache 2
Classifier: Development Status :: 3 - Alpha
Classifier: Intended Audience :: Developers
Classifier: Topic :: Software Development :: Libraries :: Python Modules
Classifier: Topic :: Utilities
Classifier: License :: OSI Approved :: Apache Software License
Classifier: Programming Language :: Python :: 3.8
Classifier: Programming Language :: Python :: 3.9
Classifier: Programming Language :: Python :: 3.10
Classifier: Programming Language :: Python :: 3.11
Requires-Python: >=3.8
License-File: LICENSE
Requires-Dist: joblib (>=1.1.0)
Requires-Dist: pyyaml (>=5.4.1)
Requires-Dist: scikit-image (>=0.18.1) ; python_version < "3.10"
Requires-Dist: numpy (>=1.21.6) ; python_version < "3.10" and python_version >= "3.9"
Requires-Dist: scikit-learn (>=0.24.2) ; python_version < "3.10" and python_version >= "3.9"
Requires-Dist: pandas (>=1.4.0) ; python_version < "3.10" and python_version >= "3.9"
Requires-Dist: astropy (>=5.1) ; python_version < "3.10" and python_version >= "3.9"
Requires-Dist: fiona (>=1.8.21) ; python_version < "3.11"
Requires-Dist: numpy (>=1.21.6) ; python_version < "3.11" and python_version >= "3.10"
Requires-Dist: scikit-learn (>=1.1.1) ; python_version < "3.11" and python_version >= "3.10"
Requires-Dist: scikit-image (>=0.19.3) ; python_version < "3.11" and python_version >= "3.10"
Requires-Dist: pandas (>=1.3.5) ; python_version < "3.11" and python_version >= "3.10"
Requires-Dist: astropy (>=5.1) ; python_version < "3.11" and python_version >= "3.10"
Requires-Dist: numpy (>=1.21.6) ; python_version < "3.9" and python_version >= "3.8"
Requires-Dist: scikit-learn (>=0.24.2) ; python_version < "3.9" and python_version >= "3.8"
Requires-Dist: pandas (>=1.4.0) ; python_version < "3.9" and python_version >= "3.8"
Requires-Dist: astropy (>=5.1) ; python_version < "3.9" and python_version >= "3.8"
Requires-Dist: numpy (>=1.23.2) ; python_version < "4.0" and python_version >= "3.11"
Requires-Dist: fiona (>=1.8.22) ; python_version < "4.0" and python_version >= "3.11"
Requires-Dist: scikit-learn (>=1.1.3) ; python_version < "4.0" and python_version >= "3.11"
Requires-Dist: scikit-image (>=0.20.0) ; python_version < "4.0" and python_version >= "3.11"
Requires-Dist: pandas (>=1.5.0) ; python_version < "4.0" and python_version >= "3.11"
Requires-Dist: astropy (>=5.2.2) ; python_version < "4.0" and python_version >= "3.11"
Provides-Extra: all
Requires-Dist: joblib (>=1.1.0) ; extra == 'all'
Requires-Dist: pyyaml (>=5.4.1) ; extra == 'all'
Requires-Dist: xdoctest (>=1.0.2) ; extra == 'all'
Requires-Dist: ubelt (>=1.2.1) ; extra == 'all'
Requires-Dist: pytest-timeout (>=1.4.2) ; extra == 'all'
Requires-Dist: requests (>=2.25.1) ; extra == 'all'
Requires-Dist: matplotlib (>=3.3.4) ; extra == 'all'
Requires-Dist: Seaborn (>=0.9.0) ; extra == 'all'
Requires-Dist: click (>=7.1.1) ; extra == 'all'
Requires-Dist: scikit-build (>=0.10.0) ; extra == 'all'
Requires-Dist: cmake (>=3.21.2) ; extra == 'all'
Requires-Dist: cython (>=0.29.32) ; extra == 'all'
Provides-Extra: all-strict
Requires-Dist: joblib (==1.1.0) ; extra == 'all-strict'
Requires-Dist: pyyaml (==5.4.1) ; extra == 'all-strict'
Requires-Dist: xdoctest (==1.0.2) ; extra == 'all-strict'
Requires-Dist: ubelt (==1.2.1) ; extra == 'all-strict'
Requires-Dist: pytest-timeout (==1.4.2) ; extra == 'all-strict'
Requires-Dist: requests (==2.25.1) ; extra == 'all-strict'
Requires-Dist: matplotlib (==3.3.4) ; extra == 'all-strict'
Requires-Dist: Seaborn (==0.9.0) ; extra == 'all-strict'
Requires-Dist: click (==7.1.1) ; extra == 'all-strict'
Requires-Dist: scikit-build (==0.10.0) ; extra == 'all-strict'
Requires-Dist: cmake (==3.21.2) ; extra == 'all-strict'
Requires-Dist: cython (==0.29.32) ; extra == 'all-strict'
Requires-Dist: scikit-image (==0.18.1) ; (python_version < "3.10") and extra == 'all-strict'
Requires-Dist: numpy (==1.21.6) ; (python_version < "3.10" and python_version >= "3.9") and extra == 'all-strict'
Requires-Dist: scikit-learn (==0.24.2) ; (python_version < "3.10" and python_version >= "3.9") and extra == 'all-strict'
Requires-Dist: pandas (==1.4.0) ; (python_version < "3.10" and python_version >= "3.9") and extra == 'all-strict'
Requires-Dist: astropy (==5.1) ; (python_version < "3.10" and python_version >= "3.9") and extra == 'all-strict'
Requires-Dist: coverage (==5.3.1) ; (python_version < "3.10" and python_version >= "3.9") and extra == 'all-strict'
Requires-Dist: pytest (==4.6.0) ; (python_version < "3.10.0" and python_version >= "3.7.0") and extra == 'all-strict'
Requires-Dist: fiona (==1.8.21) ; (python_version < "3.11") and extra == 'all-strict'
Requires-Dist: numpy (==1.21.6) ; (python_version < "3.11" and python_version >= "3.10") and extra == 'all-strict'
Requires-Dist: scikit-learn (==1.1.1) ; (python_version < "3.11" and python_version >= "3.10") and extra == 'all-strict'
Requires-Dist: scikit-image (==0.19.3) ; (python_version < "3.11" and python_version >= "3.10") and extra == 'all-strict'
Requires-Dist: pandas (==1.3.5) ; (python_version < "3.11" and python_version >= "3.10") and extra == 'all-strict'
Requires-Dist: astropy (==5.1) ; (python_version < "3.11" and python_version >= "3.10") and extra == 'all-strict'
Requires-Dist: coverage (==6.1.1) ; (python_version < "3.7" and python_version >= "3.6") and extra == 'all-strict'
Requires-Dist: pytest (==4.6.0) ; (python_version < "3.7.0" and python_version >= "3.6.0") and extra == 'all-strict'
Requires-Dist: coverage (==6.1.1) ; (python_version < "3.8" and python_version >= "3.7") and extra == 'all-strict'
Requires-Dist: numpy (==1.21.6) ; (python_version < "3.9" and python_version >= "3.8") and extra == 'all-strict'
Requires-Dist: scikit-learn (==0.24.2) ; (python_version < "3.9" and python_version >= "3.8") and extra == 'all-strict'
Requires-Dist: pandas (==1.4.0) ; (python_version < "3.9" and python_version >= "3.8") and extra == 'all-strict'
Requires-Dist: astropy (==5.1) ; (python_version < "3.9" and python_version >= "3.8") and extra == 'all-strict'
Requires-Dist: coverage (==6.1.1) ; (python_version < "3.9" and python_version >= "3.8") and extra == 'all-strict'
Requires-Dist: numpy (==1.23.2) ; (python_version < "4.0" and python_version >= "3.11") and extra == 'all-strict'
Requires-Dist: fiona (==1.8.22) ; (python_version < "4.0" and python_version >= "3.11") and extra == 'all-strict'
Requires-Dist: scikit-learn (==1.1.3) ; (python_version < "4.0" and python_version >= "3.11") and extra == 'all-strict'
Requires-Dist: scikit-image (==0.20.0) ; (python_version < "4.0" and python_version >= "3.11") and extra == 'all-strict'
Requires-Dist: pandas (==1.5.0) ; (python_version < "4.0" and python_version >= "3.11") and extra == 'all-strict'
Requires-Dist: astropy (==5.2.2) ; (python_version < "4.0" and python_version >= "3.11") and extra == 'all-strict'
Requires-Dist: coverage (==6.1.1) ; (python_version >= "3.10") and extra == 'all-strict'
Requires-Dist: pytest (==6.2.5) ; (python_version >= "3.10.0") and extra == 'all-strict'
Requires-Dist: pytest-cov (==3.0.0) ; (python_version >= "3.6.0") and extra == 'all-strict'
Requires-Dist: scikit-image (>=0.18.1) ; (python_version < "3.10") and extra == 'all'
Requires-Dist: numpy (>=1.21.6) ; (python_version < "3.10" and python_version >= "3.9") and extra == 'all'
Requires-Dist: scikit-learn (>=0.24.2) ; (python_version < "3.10" and python_version >= "3.9") and extra == 'all'
Requires-Dist: pandas (>=1.4.0) ; (python_version < "3.10" and python_version >= "3.9") and extra == 'all'
Requires-Dist: astropy (>=5.1) ; (python_version < "3.10" and python_version >= "3.9") and extra == 'all'
Requires-Dist: coverage (>=5.3.1) ; (python_version < "3.10" and python_version >= "3.9") and extra == 'all'
Requires-Dist: pytest (>=4.6.0) ; (python_version < "3.10.0" and python_version >= "3.7.0") and extra == 'all'
Requires-Dist: fiona (>=1.8.21) ; (python_version < "3.11") and extra == 'all'
Requires-Dist: numpy (>=1.21.6) ; (python_version < "3.11" and python_version >= "3.10") and extra == 'all'
Requires-Dist: scikit-learn (>=1.1.1) ; (python_version < "3.11" and python_version >= "3.10") and extra == 'all'
Requires-Dist: scikit-image (>=0.19.3) ; (python_version < "3.11" and python_version >= "3.10") and extra == 'all'
Requires-Dist: pandas (>=1.3.5) ; (python_version < "3.11" and python_version >= "3.10") and extra == 'all'
Requires-Dist: astropy (>=5.1) ; (python_version < "3.11" and python_version >= "3.10") and extra == 'all'
Requires-Dist: coverage (>=6.1.1) ; (python_version < "3.7" and python_version >= "3.6") and extra == 'all'
Requires-Dist: pytest (>=4.6.0) ; (python_version < "3.7.0" and python_version >= "3.6.0") and extra == 'all'
Requires-Dist: coverage (>=6.1.1) ; (python_version < "3.8" and python_version >= "3.7") and extra == 'all'
Requires-Dist: numpy (>=1.21.6) ; (python_version < "3.9" and python_version >= "3.8") and extra == 'all'
Requires-Dist: scikit-learn (>=0.24.2) ; (python_version < "3.9" and python_version >= "3.8") and extra == 'all'
Requires-Dist: pandas (>=1.4.0) ; (python_version < "3.9" and python_version >= "3.8") and extra == 'all'
Requires-Dist: astropy (>=5.1) ; (python_version < "3.9" and python_version >= "3.8") and extra == 'all'
Requires-Dist: coverage (>=6.1.1) ; (python_version < "3.9" and python_version >= "3.8") and extra == 'all'
Requires-Dist: numpy (>=1.23.2) ; (python_version < "4.0" and python_version >= "3.11") and extra == 'all'
Requires-Dist: fiona (>=1.8.22) ; (python_version < "4.0" and python_version >= "3.11") and extra == 'all'
Requires-Dist: scikit-learn (>=1.1.3) ; (python_version < "4.0" and python_version >= "3.11") and extra == 'all'
Requires-Dist: scikit-image (>=0.20.0) ; (python_version < "4.0" and python_version >= "3.11") and extra == 'all'
Requires-Dist: pandas (>=1.5.0) ; (python_version < "4.0" and python_version >= "3.11") and extra == 'all'
Requires-Dist: astropy (>=5.2.2) ; (python_version < "4.0" and python_version >= "3.11") and extra == 'all'
Requires-Dist: coverage (>=6.1.1) ; (python_version >= "3.10") and extra == 'all'
Requires-Dist: pytest (>=6.2.5) ; (python_version >= "3.10.0") and extra == 'all'
Requires-Dist: pytest-cov (>=3.0.0) ; (python_version >= "3.6.0") and extra == 'all'
Provides-Extra: graphics
Provides-Extra: graphics-strict
Requires-Dist: opencv-python (==3.4.15.55) ; (python_version < "3.10" and python_version >= "3.9") and extra == 'graphics-strict'
Requires-Dist: opencv-python (==4.5.4.58) ; (python_version < "3.11" and python_version >= "3.10") and extra == 'graphics-strict'
Requires-Dist: opencv-python (==3.1.0.0) ; (python_version < "3.4" and python_version >= "2.7") and extra == 'graphics-strict'
Requires-Dist: opencv-python (==3.1.0.5) ; (python_version < "3.5" and python_version >= "3.4") and extra == 'graphics-strict'
Requires-Dist: opencv-python (==3.1.0.2) ; (python_version < "3.6" and python_version >= "3.5") and extra == 'graphics-strict'
Requires-Dist: opencv-python (==3.4.13.47) ; (python_version < "3.7" and python_version >= "3.6") and extra == 'graphics-strict'
Requires-Dist: opencv-python (==3.4.15.55) ; (python_version < "3.8" and python_version >= "3.7") and extra == 'graphics-strict'
Requires-Dist: opencv-python (==3.4.15.55) ; (python_version < "3.9" and python_version >= "3.8") and extra == 'graphics-strict'
Requires-Dist: opencv-python (==4.5.5.64) ; (python_version < "4.0" and python_version >= "3.11") and extra == 'graphics-strict'
Requires-Dist: opencv-python (>=3.4.15.55) ; (python_version < "3.10" and python_version >= "3.9") and extra == 'graphics'
Requires-Dist: opencv-python (>=4.5.4.58) ; (python_version < "3.11" and python_version >= "3.10") and extra == 'graphics'
Requires-Dist: opencv-python (>=3.1.0.0) ; (python_version < "3.4" and python_version >= "2.7") and extra == 'graphics'
Requires-Dist: opencv-python (>=3.1.0.5) ; (python_version < "3.5" and python_version >= "3.4") and extra == 'graphics'
Requires-Dist: opencv-python (>=3.1.0.2) ; (python_version < "3.6" and python_version >= "3.5") and extra == 'graphics'
Requires-Dist: opencv-python (>=3.4.13.47) ; (python_version < "3.7" and python_version >= "3.6") and extra == 'graphics'
Requires-Dist: opencv-python (>=3.4.15.55) ; (python_version < "3.8" and python_version >= "3.7") and extra == 'graphics'
Requires-Dist: opencv-python (>=3.4.15.55) ; (python_version < "3.9" and python_version >= "3.8") and extra == 'graphics'
Requires-Dist: opencv-python (>=4.5.5.64) ; (python_version < "4.0" and python_version >= "3.11") and extra == 'graphics'
Provides-Extra: headless
Provides-Extra: headless-strict
Requires-Dist: opencv-python-headless (==3.4.15.55) ; (python_version < "3.10" and python_version >= "3.9") and extra == 'headless-strict'
Requires-Dist: opencv-python-headless (==4.5.4.58) ; (python_version < "3.11" and python_version >= "3.10") and extra == 'headless-strict'
Requires-Dist: opencv-python-headless (==3.4.2.16) ; (python_version < "3.4" and python_version >= "2.7") and extra == 'headless-strict'
Requires-Dist: opencv-python-headless (==3.4.2.16) ; (python_version < "3.5" and python_version >= "3.4") and extra == 'headless-strict'
Requires-Dist: opencv-python-headless (==3.4.2.16) ; (python_version < "3.6" and python_version >= "3.5") and extra == 'headless-strict'
Requires-Dist: opencv-python-headless (==3.4.13.47) ; (python_version < "3.7" and python_version >= "3.6") and extra == 'headless-strict'
Requires-Dist: opencv-python-headless (==3.4.15.55) ; (python_version < "3.8" and python_version >= "3.7") and extra == 'headless-strict'
Requires-Dist: opencv-python-headless (==3.4.15.55) ; (python_version < "3.9" and python_version >= "3.8") and extra == 'headless-strict'
Requires-Dist: opencv-python-headless (==4.5.5.64) ; (python_version < "4.0" and python_version >= "3.11") and extra == 'headless-strict'
Requires-Dist: opencv-python-headless (>=3.4.15.55) ; (python_version < "3.10" and python_version >= "3.9") and extra == 'headless'
Requires-Dist: opencv-python-headless (>=4.5.4.58) ; (python_version < "3.11" and python_version >= "3.10") and extra == 'headless'
Requires-Dist: opencv-python-headless (>=3.4.2.16) ; (python_version < "3.4" and python_version >= "2.7") and extra == 'headless'
Requires-Dist: opencv-python-headless (>=3.4.2.16) ; (python_version < "3.5" and python_version >= "3.4") and extra == 'headless'
Requires-Dist: opencv-python-headless (>=3.4.2.16) ; (python_version < "3.6" and python_version >= "3.5") and extra == 'headless'
Requires-Dist: opencv-python-headless (>=3.4.13.47) ; (python_version < "3.7" and python_version >= "3.6") and extra == 'headless'
Requires-Dist: opencv-python-headless (>=3.4.15.55) ; (python_version < "3.8" and python_version >= "3.7") and extra == 'headless'
Requires-Dist: opencv-python-headless (>=3.4.15.55) ; (python_version < "3.9" and python_version >= "3.8") and extra == 'headless'
Requires-Dist: opencv-python-headless (>=4.5.5.64) ; (python_version < "4.0" and python_version >= "3.11") and extra == 'headless'
Provides-Extra: optional
Requires-Dist: matplotlib (>=3.3.4) ; extra == 'optional'
Requires-Dist: Seaborn (>=0.9.0) ; extra == 'optional'
Requires-Dist: click (>=7.1.1) ; extra == 'optional'
Provides-Extra: optional-strict
Requires-Dist: matplotlib (==3.3.4) ; extra == 'optional-strict'
Requires-Dist: Seaborn (==0.9.0) ; extra == 'optional-strict'
Requires-Dist: click (==7.1.1) ; extra == 'optional-strict'
Provides-Extra: runtime-strict
Requires-Dist: joblib (==1.1.0) ; extra == 'runtime-strict'
Requires-Dist: pyyaml (==5.4.1) ; extra == 'runtime-strict'
Requires-Dist: scikit-image (==0.18.1) ; (python_version < "3.10") and extra == 'runtime-strict'
Requires-Dist: numpy (==1.21.6) ; (python_version < "3.10" and python_version >= "3.9") and extra == 'runtime-strict'
Requires-Dist: scikit-learn (==0.24.2) ; (python_version < "3.10" and python_version >= "3.9") and extra == 'runtime-strict'
Requires-Dist: pandas (==1.4.0) ; (python_version < "3.10" and python_version >= "3.9") and extra == 'runtime-strict'
Requires-Dist: astropy (==5.1) ; (python_version < "3.10" and python_version >= "3.9") and extra == 'runtime-strict'
Requires-Dist: fiona (==1.8.21) ; (python_version < "3.11") and extra == 'runtime-strict'
Requires-Dist: numpy (==1.21.6) ; (python_version < "3.11" and python_version >= "3.10") and extra == 'runtime-strict'
Requires-Dist: scikit-learn (==1.1.1) ; (python_version < "3.11" and python_version >= "3.10") and extra == 'runtime-strict'
Requires-Dist: scikit-image (==0.19.3) ; (python_version < "3.11" and python_version >= "3.10") and extra == 'runtime-strict'
Requires-Dist: pandas (==1.3.5) ; (python_version < "3.11" and python_version >= "3.10") and extra == 'runtime-strict'
Requires-Dist: astropy (==5.1) ; (python_version < "3.11" and python_version >= "3.10") and extra == 'runtime-strict'
Requires-Dist: numpy (==1.21.6) ; (python_version < "3.9" and python_version >= "3.8") and extra == 'runtime-strict'
Requires-Dist: scikit-learn (==0.24.2) ; (python_version < "3.9" and python_version >= "3.8") and extra == 'runtime-strict'
Requires-Dist: pandas (==1.4.0) ; (python_version < "3.9" and python_version >= "3.8") and extra == 'runtime-strict'
Requires-Dist: astropy (==5.1) ; (python_version < "3.9" and python_version >= "3.8") and extra == 'runtime-strict'
Requires-Dist: numpy (==1.23.2) ; (python_version < "4.0" and python_version >= "3.11") and extra == 'runtime-strict'
Requires-Dist: fiona (==1.8.22) ; (python_version < "4.0" and python_version >= "3.11") and extra == 'runtime-strict'
Requires-Dist: scikit-learn (==1.1.3) ; (python_version < "4.0" and python_version >= "3.11") and extra == 'runtime-strict'
Requires-Dist: scikit-image (==0.20.0) ; (python_version < "4.0" and python_version >= "3.11") and extra == 'runtime-strict'
Requires-Dist: pandas (==1.5.0) ; (python_version < "4.0" and python_version >= "3.11") and extra == 'runtime-strict'
Requires-Dist: astropy (==5.2.2) ; (python_version < "4.0" and python_version >= "3.11") and extra == 'runtime-strict'
Provides-Extra: tests
Requires-Dist: xdoctest (>=1.0.2) ; extra == 'tests'
Requires-Dist: ubelt (>=1.2.1) ; extra == 'tests'
Requires-Dist: pytest-timeout (>=1.4.2) ; extra == 'tests'
Requires-Dist: requests (>=2.25.1) ; extra == 'tests'
Provides-Extra: tests-strict
Requires-Dist: xdoctest (==1.0.2) ; extra == 'tests-strict'
Requires-Dist: ubelt (==1.2.1) ; extra == 'tests-strict'
Requires-Dist: pytest-timeout (==1.4.2) ; extra == 'tests-strict'
Requires-Dist: requests (==2.25.1) ; extra == 'tests-strict'
Requires-Dist: coverage (==5.3.1) ; (python_version < "3.10" and python_version >= "3.9") and extra == 'tests-strict'
Requires-Dist: pytest (==4.6.0) ; (python_version < "3.10.0" and python_version >= "3.7.0") and extra == 'tests-strict'
Requires-Dist: coverage (==6.1.1) ; (python_version < "3.7" and python_version >= "3.6") and extra == 'tests-strict'
Requires-Dist: pytest (==4.6.0) ; (python_version < "3.7.0" and python_version >= "3.6.0") and extra == 'tests-strict'
Requires-Dist: coverage (==6.1.1) ; (python_version < "3.8" and python_version >= "3.7") and extra == 'tests-strict'
Requires-Dist: coverage (==6.1.1) ; (python_version < "3.9" and python_version >= "3.8") and extra == 'tests-strict'
Requires-Dist: coverage (==6.1.1) ; (python_version >= "3.10") and extra == 'tests-strict'
Requires-Dist: pytest (==6.2.5) ; (python_version >= "3.10.0") and extra == 'tests-strict'
Requires-Dist: pytest-cov (==3.0.0) ; (python_version >= "3.6.0") and extra == 'tests-strict'
Requires-Dist: coverage (>=5.3.1) ; (python_version < "3.10" and python_version >= "3.9") and extra == 'tests'
Requires-Dist: pytest (>=4.6.0) ; (python_version < "3.10.0" and python_version >= "3.7.0") and extra == 'tests'
Requires-Dist: coverage (>=6.1.1) ; (python_version < "3.7" and python_version >= "3.6") and extra == 'tests'
Requires-Dist: pytest (>=4.6.0) ; (python_version < "3.7.0" and python_version >= "3.6.0") and extra == 'tests'
Requires-Dist: coverage (>=6.1.1) ; (python_version < "3.8" and python_version >= "3.7") and extra == 'tests'
Requires-Dist: coverage (>=6.1.1) ; (python_version < "3.9" and python_version >= "3.8") and extra == 'tests'
Requires-Dist: coverage (>=6.1.1) ; (python_version >= "3.10") and extra == 'tests'
Requires-Dist: pytest (>=6.2.5) ; (python_version >= "3.10.0") and extra == 'tests'
Requires-Dist: pytest-cov (>=3.0.0) ; (python_version >= "3.6.0") and extra == 'tests'
